{
  "id": "c8",
  "title": "Audyt Klauzuli 8: Sprzęt (Hardware)",
  "content": [
    {
      "type": "heading",
      "level": 3,
      "text": "C.8.1 Wymagania ogólne"
    },
    {
      "type": "informative",
      "text": "C.8.1 Wymagania ogólne\nKlauzula 8.1.1 jest doradcza i nie zawiera wymagań do testowania.\n"
    },
    {
      "type": "heading",
      "level": 4,
      "text": "C.8.1.2 Standardowe złącza"
    },
    {
      "type": "test",
      "preconditions": [
        "1. TIK zapewnia punkty podłączenia urządzeń wejścia lub wyjścia użytkownika."
      ],
      "procedure": [
        "1. Sprawdź, czy jeden typ połączenia jest zgodny z branżowym, niewłasnościowym formatem.",
        "2. Sprawdź, czy jeden typ połączenia jest zgodny z branżowym, niewłasnościowym formatem poprzez użycie komercyjnie dostępnych adapterów."
      ],
      "form": {
        "inputs": [
          {
            "value": "pass",
            "label": "<strong>Zaliczone:</strong> Sprawdzenie 1 lub 2 jest prawdziwe."
          },
          {
            "value": "fail",
            "label": "<strong>Niezaliczone:</strong> Sprawdzenia 1 i 2 są fałszywe."
          },
          {
            "value": "na",
            "label": "<strong>Nie dotyczy:</strong> Warunek wstępny 1 nie jest spełniony."
          }
        ],
        "legend": "Wybierz wynik dla C.8.1.2 Standardowe złącza:",
        "noteId": "notes-c8-1-2"
      },
      "evaluationType": "Inspection"
    },
    {
      "type": "heading",
      "level": 4,
      "text": "C.8.1.3 Kolor"
    },
    {
      "type": "test",
      "preconditions": [
        "1. Aspekty sprzętowe TIK przekazują informacje wizualne za pomocą kodowania kolorami jako sposobu na wskazanie działania, wywołanie odpowiedzi lub rozróżnienie elementu wizualnego."
      ],
      "procedure": [
        "1. Sprawdź, czy zapewniono alternatywną formę kodowania wizualnego."
      ],
      "form": {
        "inputs": [
          {
            "value": "pass",
            "label": "<strong>Zaliczone:</strong> Sprawdzenie 1 jest prawdziwe."
          },
          {
            "value": "fail",
            "label": "<strong>Niezaliczone:</strong> Sprawdzenie 1 jest fałszywe."
          },
          {
            "value": "na",
            "label": "<strong>Nie dotyczy:</strong> Warunek wstępny 1 nie jest spełniony."
          }
        ],
        "legend": "Wybierz wynik dla C.8.1.3 Kolor:",
        "noteId": "notes-c8-1-3"
      },
      "evaluationType": "Inspection"
    },
    {
      "type": "heading",
      "level": 3,
      "text": "C.8.2 Produkty sprzętowe z wyjściem mowy"
    },
    {
      "type": "heading",
      "level": 4,
      "text": "C.8.2.1 Wzmocnienie głośności mowy"
    },
    {
      "type": "heading",
      "level": 5,
      "text": "C.8.2.1.1 Zakres głośności mowy"
    },
    {
      "type": "test",
      "preconditions": [
        "1. Sprzęt TIK ma wyjście mowy."
      ],
      "procedure": [
        "1. Sprawdź, czy TIK jest certyfikowany zgodnie z ANSI/TIA-4965 [i.2].",
        "2. Zmierz poziom (w dB) wyjścia mowy przy najniższym ustawieniu głośności.",
        "3. Zmierz poziom (w dB) wyjścia mowy przy najwyższym ustawieniu głośności.",
        "4. Sprawdź, czy zakres między 2 a 3 jest większy lub równy 18 dB."
      ],
      "form": {
        "inputs": [
          {
            "value": "pass",
            "label": "<strong>Zaliczone:</strong> Sprawdzenie 1 lub 4 jest prawdziwe."
          },
          {
            "value": "fail",
            "label": "<strong>Niezaliczone:</strong> Sprawdzenie 1 i 4 są fałszywe."
          },
          {
            "value": "na",
            "label": "<strong>Nie dotyczy:</strong> Warunek wstępny 1 nie jest spełniony."
          }
        ],
        "legend": "Wybierz wynik dla C.8.2.1.1 Zakres głośności mowy:",
        "noteId": "notes-c8-2-1-1"
      },
      "evaluationType": "Inspection based on measurement data"
    },
    {
      "type": "heading",
      "level": 5,
      "text": "C.8.2.1.2 Przyrostowa kontrola głośności"
    },
    {
      "type": "test",
      "preconditions": [
        "1. Sprzęt TIK ma wyjście mowy.",
        "2. Kontrola głośności jest przyrostowa."
      ],
      "procedure": [
        "1. Zmierz poziom (w dB) wyjścia mowy przy najniższym ustawieniu głośności.",
        "2. Sprawdź, czy jeden pośredni krok zapewnia poziom o 12 dB wyższy niż najniższy poziom zmierzony w kroku 1."
      ],
      "form": {
        "inputs": [
          {
            "value": "pass",
            "label": "<strong>Zaliczone:</strong> Sprawdzenie 2 jest prawdziwe."
          },
          {
            "value": "fail",
            "label": "<strong>Niezaliczone:</strong> Sprawdzenie 2 jest fałszywe."
          },
          {
            "value": "na",
            "label": "<strong>Nie dotyczy:</strong> Warunek wstępny 1 lub 2 nie jest spełniony."
          }
        ],
        "legend": "Wybierz wynik dla C.8.2.1.2 Przyrostowa kontrola głośności:",
        "noteId": "notes-c8-2-1-2"
      },
      "evaluationType": "Inspection based on measurement data"
    },
    {
      "type": "heading",
      "level": 4,
      "text": "C.8.2.2 Sprzężenie magnetyczne"
    },
    {
      "type": "heading",
      "level": 5,
      "text": "C.8.2.2.1 Urządzenia stacjonarne"
    },
    {
      "type": "test",
      "preconditions": [
        "1. Sprzęt TIK jest stacjonarnym urządzeniem komunikacyjnym z wyjściem audio, które normalnie trzyma się przy uchu."
      ],
      "procedure": [
        "1. Sprawdź, czy TIK jest certyfikowany zgodnie z TIA-1083-A [i.24].",
        "2. Pomiary są wykonane zgodnie z ETSI ES 200 381-1 [2], co dowodzi, że wymagania zdefiniowane w tym standardzie są spełnione.",
        "3. TIK posiada symbol \"T\" określony w ETSI ETS 300 381 [1]."
      ],
      "form": {
        "inputs": [
          {
            "value": "pass",
            "label": "<strong>Zaliczone:</strong> Sprawdzenie 1 lub 2 jest prawdziwe ORAZ sprawdzenie 3 jest prawdziwe."
          },
          {
            "value": "fail",
            "label": "<strong>Niezaliczone:</strong> Sprawdzenia 1 i 2 są fałszywe LUB sprawdzenie 3 jest fałszywe."
          },
          {
            "value": "na",
            "label": "<strong>Nie dotyczy:</strong> Warunek wstępny 1 nie jest spełniony."
          }
        ],
        "legend": "Wybierz wynik dla C.8.2.2.1 Urządzenia stacjonarne:",
        "noteId": "notes-c8-2-2-1"
      },
      "evaluationType": "Inspection based on measurement data"
    },
    {
      "type": "heading",
      "level": 5,
      "text": "C.8.2.2.2 Urządzenia komunikacji bezprzewodowej"
    },
    {
      "type": "test",
      "preconditions": [
        "1. Sprzęt TIK jest bezprzewodowym urządzeniem komunikacyjnym, które normalnie trzyma się przy uchu."
      ],
      "procedure": [
        "1. Sprawdź, czy TIK jest certyfikowany zgodnie z ANSI/IEEE C63.19 [i.1].",
        "2. Sprawdź, czy TIK zapewnia środek sprzężenia magnetycznego z technologiami słuchowymi, który spełnia wymagania ETSI ES 200 381-2 [3]."
      ],
      "form": {
        "inputs": [
          {
            "value": "pass",
            "label": "<strong>Zaliczone:</strong> Sprawdzenie 1 lub 2 jest prawdziwe."
          },
          {
            "value": "fail",
            "label": "<strong>Niezaliczone:</strong> Sprawdzenia 1 i 2 są fałszywe."
          },
          {
            "value": "na",
            "label": "<strong>Nie dotyczy:</strong> Warunek wstępny 1 nie jest spełniony."
          }
        ],
        "legend": "Wybierz wynik dla C.8.2.2.2 Urządzenia komunikacji bezprzewodowej:",
        "noteId": "notes-c8-2-2-2"
      },
      "evaluationType": "Inspection based on measurement data"
    },
    {
      "type": "heading",
      "level": 3,
      "text": "C.8.3 TIK stacjonarne"
    },
    {
      "type": "informative",
      "text": "C.8.3 TIK stacjonarne\nKlauzula 8.3.0 jest doradcza i nie zawiera wymagań do testowania.\n"
    },
    {
      "type": "heading",
      "level": 4,
      "text": "C.8.3.1 Zasięg do przodu lub boczny"
    },
    {
      "type": "test",
      "preconditions": [
        "1. TIK jest TIK-iem stacjonarnym."
      ],
      "procedure": [
        "1. Sprawdź, czy TIK jest zgodny z klauzulą 8.3.2.2.",
        "2. Sprawdź, czy TIK jest zgodny z klauzulą 8.3.2.3."
      ],
      "form": {
        "inputs": [
          {
            "value": "pass",
            "label": "<strong>Zaliczone:</strong> Sprawdzenie 1 lub 2 jest prawdziwe."
          },
          {
            "value": "fail",
            "label": "<strong>Niezaliczone:</strong> Sprawdzenia 1 i 2 są fałszywe."
          },
          {
            "value": "na",
            "label": "<strong>Nie dotyczy:</strong> Warunek wstępny 1 nie jest spełniony."
          }
        ],
        "legend": "Wybierz wynik dla C.8.3.1 Zasięg do przodu lub boczny:",
        "noteId": "notes-c8-3-1"
      },
      "evaluationType": "Inspection"
    },
    {
      "type": "heading",
      "level": 4,
      "text": "C.8.3.2 Zasięg do przodu"
    },
    {
      "type": "heading",
      "level": 5,
      "text": "C.8.3.2.1 Wysoki zasięg do przodu bez przeszkód"
    },
    {
      "type": "test",
      "preconditions": [
        "1. TIK jest TIK-iem stacjonarnym.",
        "2. Żadna część TIK-u stacjonarnego nie utrudnia zasięgu do przodu."
      ],
      "procedure": [
        "1. Sprawdź, czy co najmniej jeden z każdego typu części obsługiwalnej znajduje się nie wyżej niż 1200 mm (48 cali) nad podłogą przestrzeni dostępowej."
      ],
      "form": {
        "inputs": [
          {
            "value": "pass",
            "label": "<strong>Zaliczone:</strong> Sprawdzenie 1 jest prawdziwe."
          },
          {
            "value": "fail",
            "label": "<strong>Niezaliczone:</strong> Sprawdzenie 1 jest fałszywe."
          },
          {
            "value": "na",
            "label": "<strong>Nie dotyczy:</strong> Warunek wstępny 1 lub 2 nie jest spełniony."
          }
        ],
        "legend": "Wybierz wynik dla C.8.3.2.1 Wysoki zasięg do przodu bez przeszkód:",
        "noteId": "notes-c8-3-2-1"
      },
      "evaluationType": "Inspection and measurement"
    },
    {
      "type": "heading",
      "level": 5,
      "text": "C.8.3.2.2 Niski zasięg do przodu bez przeszkód"
    },
    {
      "type": "test",
      "preconditions": [
        "1. TIK jest TIK-iem stacjonarnym.",
        "2. Żadna część TIK-u stacjonarnego nie utrudnia zasięgu do przodu."
      ],
      "procedure": [
        "1. Sprawdź, czy co najmniej jeden z każdego typu części obsługiwalnej znajduje się nie niżej niż 380 mm (15 cali) nad podłogą przestrzeni dostępowej."
      ],
      "form": {
        "inputs": [
          {
            "value": "pass",
            "label": "<strong>Zaliczone:</strong> Sprawdzenie 1 jest prawdziwe."
          },
          {
            "value": "fail",
            "label": "<strong>Niezaliczone:</strong> Sprawdzenie 1 jest fałszywe."
          },
          {
            "value": "na",
            "label": "<strong>Nie dotyczy:</strong> Warunek wstępny 1 lub 2 nie jest spełniony."
          }
        ],
        "legend": "Wybierz wynik dla C.8.3.2.2 Niski zasięg do przodu bez przeszkód:",
        "noteId": "notes-c8-3-2-2"
      },
      "evaluationType": "Inspection and measurement"
    },
    {
      "type": "heading",
      "level": 4,
      "text": "C.8.3.3 Zasięg boczny"
    },
    {
      "type": "heading",
      "level": 5,
      "text": "C.8.3.3.1 Wysoki zasięg boczny bez przeszkód"
    },
    {
      "type": "test",
      "preconditions": [
        "1. TIK jest TIK-iem stacjonarnym.",
        "2. Zasięg boczny jest niezakłócony lub jest zakłócony przez element będący integralną częścią TIK-u stacjonarnego, który ma mniej niż 510 mm (20 cali)."
      ],
      "procedure": [
        "1. Sprawdź, czy wysoki zasięg boczny do co najmniej jednego z każdego typu części obsługiwalnej nie jest wyższy niż 1220 mm (48 cali) nad podłogą przestrzeni dostępowej."
      ],
      "form": {
        "inputs": [
          {
            "value": "pass",
            "label": "<strong>Zaliczone:</strong> Sprawdzenie 1 jest prawdziwe."
          },
          {
            "value": "fail",
            "label": "<strong>Niezaliczone:</strong> Sprawdzenie 1 jest fałszywe."
          },
          {
            "value": "na",
            "label": "<strong>Nie dotyczy:</strong> Warunek wstępny 1 lub 2 nie jest spełniony."
          }
        ],
        "legend": "Wybierz wynik dla C.8.3.3.1 Wysoki zasięg boczny bez przeszkód:",
        "noteId": "notes-c8-3-3-1"
      },
      "evaluationType": "Inspection and measurement"
    },
    {
      "type": "heading",
      "level": 5,
      "text": "C.8.3.3.2 Niski zasięg boczny bez przeszkód"
    },
    {
      "type": "test",
      "preconditions": [
        "1. TIK jest TIK-iem stacjonarnym.",
        "2. Zasięg boczny jest niezakłócony lub jest zakłócony przez element będący integralną częścią TIK-u stacjonarnego, który ma mniej niż 510 mm (20 cali)."
      ],
      "procedure": [
        "1. Sprawdź, czy niski zasięg boczny do co najmniej jednego z każdego typu części obsługiwalnej jest większy lub równy 380 mm (15 cali) nad podłogą przestrzeni dostępowej."
      ],
      "form": {
        "inputs": [
          {
            "value": "pass",
            "label": "<strong>Zaliczone:</strong> Sprawdzenie 1 jest prawdziwe."
          },
          {
            "value": "fail",
            "label": "<strong>Niezaliczone:</strong> Sprawdzenie 1 jest fałszywe."
          },
          {
            "value": "na",
            "label": "<strong>Nie dotyczy:</strong> Warunek wstępny 1 lub 2 nie jest spełniony."
          }
        ],
        "legend": "Wybierz wynik dla C.8.3.3.2 Niski zasięg boczny bez przeszkód:",
        "noteId": "notes-c8-3-3-2"
      },
      "evaluationType": "Inspection and measurement"
    },
    {
      "type": "heading",
      "level": 4,
      "text": "C.8.3.4 Wolna przestrzeń podłogowa"
    },
    {
      "type": "heading",
      "level": 5,
      "text": "C.8.3.4.1 Zmiana poziomu"
    },
    {
      "type": "test",
      "preconditions": [
        "1. TIK jest TIK-iem stacjonarnym.",
        "2. Wewnątrz TIK znajduje się podłoga.",
        "3. Podłoga ma zmianę poziomu."
      ],
      "procedure": [
        "1. Jeśli zmiana poziomu jest pochyła, sprawdź, czy ma nachylenie mniejsze niż 1:48.",
        "2. Jeśli występuje pionowa zmiana poziomu podłogi, sprawdź, czy jest mniejsza lub równa 6,4 mm.",
        "3. Jeśli występuje pionowa lub pochyła zmiana poziomu podłogi, sprawdź, czy nachylenie nie jest większe niż 1:2."
      ],
      "form": {
        "inputs": [
          {
            "value": "pass",
            "label": "<strong>Zaliczone:</strong> Sprawdzenie 1, 2 lub 3 jest prawdziwe."
          },
          {
            "value": "fail",
            "label": "<strong>Niezaliczone:</strong> Sprawdzenia 1, 2 i 3 są fałszywe."
          },
          {
            "value": "na",
            "label": "<strong>Nie dotyczy:</strong> Warunek wstępny 1, 2 lub 3 nie jest spełniony."
          }
        ],
        "legend": "Wybierz wynik dla C.8.3.4.1 Zmiana poziomu:",
        "noteId": "notes-c8-3-4-1"
      },
      "evaluationType": "Inspection and measurement"
    },
    {
      "type": "heading",
      "level": 5,
      "text": "C.8.3.4.2 Wolna przestrzeń podłogowa"
    },
    {
      "type": "test",
      "preconditions": [
        "1. TIK jest TIK-iem stacjonarnym.",
        "2. Wewnątrz znajduje się obszar operacyjny."
      ],
      "procedure": [
        "1. Sprawdź, czy istnieje wolna przestrzeń podłogowa o minimalnych wymiarach prostokątnych 760 mm na jednej krawędzi i 1220 mm na drugiej."
      ],
      "form": {
        "inputs": [
          {
            "value": "pass",
            "label": "<strong>Zaliczone:</strong> Sprawdzenie 1 jest prawdziwe."
          },
          {
            "value": "fail",
            "label": "<strong>Niezaliczone:</strong> Sprawdzenie 1 jest fałszywe."
          },
          {
            "value": "na",
            "label": "<strong>Nie dotyczy:</strong> Warunek wstępny 1 lub 2 nie jest spełniony."
          }
        ],
        "legend": "Wybierz wynik dla C.8.3.4.2 Wolna przestrzeń podłogowa:",
        "noteId": "notes-c8-3-4-2"
      },
      "evaluationType": "Inspection and measurement"
    },
    {
      "type": "heading",
      "level": 4,
      "text": "C.8.3.5 Widoczność"
    },
    {
      "type": "test",
      "preconditions": [
        "1. TIK jest TIK-iem stacjonarnym.",
        "2. Dostarczono jeden lub więcej ekranów."
      ],
      "procedure": [
        "1. Sprawdź, czy co najmniej jeden z każdego typu ekranu jest umieszczony tak, aby informacje na ekranie były czytelne z punktu znajdującego się 1015 mm (40 cali) nad środkiem podłogi obszaru operacyjnego."
      ],
      "form": {
        "inputs": [
          {
            "value": "pass",
            "label": "<strong>Zaliczone:</strong> Sprawdzenie 1 jest prawdziwe."
          },
          {
            "value": "fail",
            "label": "<strong>Niezaliczone:</strong> Sprawdzenie 1 jest fałszywe."
          },
          {
            "value": "na",
            "label": "<strong>Nie dotyczy:</strong> Warunek wstępny 1 lub 2 nie jest spełniony."
          }
        ],
        "legend": "Wybierz wynik dla C.8.3.5 Widoczność:",
        "noteId": "notes-c8-3-5"
      },
      "evaluationType": "Inspection and measurement"
    },
    {
      "type": "heading",
      "level": 4,
      "text": "C.8.3.6 Instrukcje instalacji"
    },
    {
      "type": "test",
      "preconditions": [
        "1. TIK jest TIK-iem stacjonarnym."
      ],
      "procedure": [
        "1. Sprawdź, czy udostępniono instrukcje instalacji.",
        "2. Sprawdź, czy instrukcje zawierają wskazówki, jak zainstalować TIK w sposób zapewniający zgodność wymiarów zainstalowanego TIK z klauzulami 8.3.2 do 8.3.4.",
        "3. Sprawdź, czy instrukcje informują, że instalatorzy powinni również uwzględnić obowiązujące wymagania dotyczące dostępności środowiska zbudowanego w odniesieniu do instalacji TIK."
      ],
      "form": {
        "inputs": [
          {
            "value": "pass",
            "label": "<strong>Zaliczone:</strong> Sprawdzenia 1, 2 i 3 są prawdziwe."
          },
          {
            "value": "fail",
            "label": "<strong>Niezaliczone:</strong> Sprawdzenie 1, 2 lub 3 jest fałszywe."
          },
          {
            "value": "na",
            "label": "<strong>Nie dotyczy:</strong> Warunek wstępny 1 nie jest spełniony."
          }
        ],
        "legend": "Wybierz wynik dla C.8.3.6 Instrukcje instalacji:",
        "noteId": "notes-c8-3-6"
      },
      "evaluationType": "Inspection and measurement"
    },
    {
      "type": "heading",
      "level": 3,
      "text": "C.8.4 Mechanicznie obsługiwane części"
    },
    {
      "type": "heading",
      "level": 4,
      "text": "C.8.4.1 Klawisze numeryczne"
    },
    {
      "type": "test",
      "preconditions": [
        "1. TIK ma fizyczne klawisze numeryczne ułożone w 12-klawiszowym układzie klawiatury telefonicznej."
      ],
      "procedure": [
        "1. Sprawdź, czy klawisz z cyfrą pięć jest dotykowo odróżnialny od pozostałych klawiszy klawiatury."
      ],
      "form": {
        "inputs": [
          {
            "value": "pass",
            "label": "<strong>Zaliczone:</strong> Sprawdzenie 1 jest prawdziwe."
          },
          {
            "value": "fail",
            "label": "<strong>Niezaliczone:</strong> Sprawdzenie 1 jest fałszywe."
          },
          {
            "value": "na",
            "label": "<strong>Nie dotyczy:</strong> Warunek wstępny 1 nie jest spełniony."
          }
        ],
        "legend": "Wybierz wynik dla C.8.4.1 Klawisze numeryczne:",
        "noteId": "notes-c8-4-1"
      },
      "evaluationType": "Inspection"
    },
    {
      "type": "heading",
      "level": 4,
      "text": "C.8.4.2 Obsługa części mechanicznych"
    },
    {
      "type": "heading",
      "level": 5,
      "text": "C.8.4.2.1 Sposób obsługi części mechanicznych"
    },
    {
      "type": "test",
      "preconditions": [
        "1. TIK ma części obsługiwalne, które wymagają chwytania, szczypania lub skręcania nadgarstka do obsługi."
      ],
      "procedure": [
        "1. Sprawdź, czy istnieje alternatywny, dostępny sposób obsługi, który nie wymaga tych działań."
      ],
      "form": {
        "inputs": [
          {
            "value": "pass",
            "label": "<strong>Zaliczone:</strong> Sprawdzenie 1 jest prawdziwe."
          },
          {
            "value": "fail",
            "label": "<strong>Niezaliczone:</strong> Sprawdzenie 1 jest fałszywe."
          },
          {
            "value": "na",
            "label": "<strong>Nie dotyczy:</strong> Warunek wstępny 1 nie jest spełniony."
          }
        ],
        "legend": "Wybierz wynik dla C.8.4.2.1 Sposób obsługi części mechanicznych:",
        "noteId": "notes-c8-4-2-1"
      },
      "evaluationType": "Inspection"
    },
    {
      "type": "heading",
      "level": 5,
      "text": "C.8.4.2.2 Siła obsługi części mechanicznych"
    },
    {
      "type": "test",
      "preconditions": [
        "1. TIK ma kontrolkę, która wymaga siły większej niż 22,2 N do obsługi."
      ],
      "procedure": [
        "1. Sprawdź, czy zapewniono dostępny alternatywny sposób obsługi, który wymaga siły mniejszej lub równej 22,2 N."
      ],
      "form": {
        "inputs": [
          {
            "value": "pass",
            "label": "<strong>Zaliczone:</strong> Sprawdzenie 1 jest prawdziwe."
          },
          {
            "value": "fail",
            "label": "<strong>Niezaliczone:</strong> Sprawdzenie 1 jest fałszywe."
          },
          {
            "value": "na",
            "label": "<strong>Nie dotyczy:</strong> Warunek wstępny 1 nie jest spełniony."
          }
        ],
        "legend": "Wybierz wynik dla C.8.4.2.2 Siła obsługi części mechanicznych:",
        "noteId": "notes-c8-4-2-2"
      },
      "evaluationType": "Inspection and measurement"
    },
    {
      "type": "heading",
      "level": 4,
      "text": "C.8.4.3 Klucze, bilety i karty opłat"
    },
    {
      "type": "test",
      "preconditions": [
        "1. TIK dostarcza klucze, bilety lub karty opłat, a ich orientacja jest ważna dla dalszego użytkowania."
      ],
      "procedure": [
        "1. Sprawdź, czy klucze, bilety lub karty opłat mają orientację, która jest dotykowo rozróżnialna."
      ],
      "form": {
        "inputs": [
          {
            "value": "pass",
            "label": "<strong>Zaliczone:</strong> Sprawdzenie 1 jest prawdziwe."
          },
          {
            "value": "fail",
            "label": "<strong>Niezaliczone:</strong> Sprawdzenie 1 jest fałszywe."
          },
          {
            "value": "na",
            "label": "<strong>Nie dotyczy:</strong> Warunek wstępny 1 nie jest spełniony."
          }
        ],
        "legend": "Wybierz wynik dla C.8.4.3 Klucze, bilety i karty opłat:",
        "noteId": "notes-c8-4-3"
      },
      "evaluationType": "Inspection and measurement"
    },
    {
      "type": "heading",
      "level": 3,
      "text": "C.8.5 Dotykowe wskazanie trybu mowy"
    },
    {
      "type": "test",
      "preconditions": [
        "1. TIK jest przeznaczony do użytku współdzielonego.",
        "2. Dostępne jest wyjście mowy."
      ],
      "procedure": [
        "1. Sprawdź, czy zapewniono dotykowe wskazanie sposobu inicjowania trybu mowy."
      ],
      "form": {
        "inputs": [
          {
            "value": "pass",
            "label": "<strong>Zaliczone:</strong> Sprawdzenie 1 jest prawdziwe."
          },
          {
            "value": "fail",
            "label": "<strong>Niezaliczone:</strong> Sprawdzenie 1 jest fałszywe."
          },
          {
            "value": "na",
            "label": "<strong>Nie dotyczy:</strong> Warunek wstępny 1 lub 2 nie jest spełniony."
          }
        ],
        "legend": "Wybierz wynik dla C.8.5 Dotykowe wskazanie trybu mowy:",
        "noteId": "notes-c8-5"
      },
      "evaluationType": "Inspection and measurement"
    }
  ]
}