{
  "id": "c9",
  "title": "Internet",
  "nodes": [
    {
      "type": "heading",
      "level": 2,
      "text": "Internet"
    },
    {
      "type": "heading",
      "level": 3,
      "id": "res-c-9-0",
      "title": "Postanowienia ogólne (informacyjne)",
      "text": "Postanowienia ogólne (informacyjne)"
    },
    {
      "type": "heading",
      "level": 3,
      "id": "res-c-9-1",
      "title": "Postrzegalność",
      "text": "Postrzegalność"
    },
    {
      "type": "heading",
      "level": 4,
      "id": "res-c-9-1-1",
      "title": "Alternatywy tekstowe",
      "text": "Alternatywy tekstowe"
    },
    {
      "type": "test",
      "level": 5,
      "id": "res-c-9-1-1-1",
      "title": "Treść nietekstowa",
      "text": ". Sprawdzić, czy strona internetowa spełnia kryterium sukcesu WCAG 2.1 – 1.1.1 Treść nietekstowa",
      "assessmentType": "Kontrola",
      "preconditions": [
        ". ICT jest stroną internetową"
      ],
      "procedure": [
        ". Sprawdzić, czy strona internetowa spełnia kryterium sukcesu WCAG 2.1 – 1.1.1 Treść nietekstowa"
      ],
      "results": [
        {
          "type": "Nie dotyczy",
          "label": "Nie spełniono warunku wstępnego 1 lub strona internetowa nie zawiera treści odpowiadającej kryterium sukcesu WCAG 2.1 – 1.1.1 Treść nietekstowa"
        }
      ]
    },
    {
      "type": "heading",
      "level": 4,
      "id": "res-c-9-1-2",
      "title": "Multimedia",
      "text": "Multimedia"
    },
    {
      "type": "test",
      "level": 5,
      "id": "res-c-9-1-2-1",
      "title": "Tylko audio lub tylko wideo (nagranie)",
      "text": ". Sprawdzić, czy strona internetowa spełnia kryterium sukcesu WCAG 2.1 – 1.2.1 Tylko audio lub tylko wideo (nagranie)",
      "assessmentType": "Kontrola",
      "preconditions": [
        ". ICT jest stroną internetową"
      ],
      "procedure": [
        ". Sprawdzić, czy strona internetowa spełnia kryterium sukcesu WCAG 2.1 – 1.2.1 Tylko audio lub tylko wideo (nagranie)"
      ],
      "results": [
        {
          "type": "Nie dotyczy",
          "label": "Nie spełniono warunku wstępnego 1 lub strona internetowa nie zawiera treści odpowiadającej kryterium sukcesu WCAG 2.1 – 1.2.1 Tylko audio lub tylko wideo (nagranie)"
        }
      ]
    },
    {
      "type": "test",
      "level": 5,
      "id": "res-c-9-1-2-2",
      "title": "Napisy rozszerzone (nagranie)",
      "text": ". Sprawdzić, czy strona internetowa spełnia kryterium sukcesu WCAG 2.1 – 1.2.2 Napisy rozszerzone (nagranie)",
      "assessmentType": "Kontrola",
      "preconditions": [
        ". ICT jest stroną internetową"
      ],
      "procedure": [
        ". Sprawdzić, czy strona internetowa spełnia kryterium sukcesu WCAG 2.1 – 1.2.2 Napisy rozszerzone (nagranie)"
      ],
      "results": [
        {
          "type": "Nie dotyczy",
          "label": "Nie spełniono warunku wstępnego 1 lub strona internetowa nie zawiera treści odpowiadającej kryterium sukcesu WCAG 2.1 – 1.2.2 Napisy rozszerzone (nagranie)"
        }
      ]
    },
    {
      "type": "test",
      "level": 5,
      "id": "res-c-9-1-2-3",
      "title": "Audiodeskrypcja lub alternatywa tekstowa dla mediów (nagranie)",
      "text": ". Sprawdzić, czy strona internetowa spełnia kryterium sukcesu WCAG 2.1 – 1.2.3 Audiodeskrypcja lub alternatywa tekstowa dla mediów (nagranie)",
      "assessmentType": "Kontrola",
      "preconditions": [
        ". ICT jest stroną internetową"
      ],
      "procedure": [
        ". Sprawdzić, czy strona internetowa spełnia kryterium sukcesu WCAG 2.1 – 1.2.3 Audiodeskrypcja lub alternatywa tekstowa dla mediów (nagranie)"
      ],
      "results": [
        {
          "type": "Nie dotyczy",
          "label": "Nie spełniono warunku wstępnego 1 lub strona internetowa nie zawiera treści odpowiadającej kryterium sukcesu WCAG 2.1 – 1.2.3 Audiodeskrypcja lub alternatywa tekstowa dla mediów (nagranie)"
        }
      ]
    },
    {
      "type": "test",
      "level": 5,
      "id": "res-c-9-1-2-4",
      "title": "Napisy rozszerzone (na żywo)",
      "text": ". Sprawdzić, czy strona internetowa spełnia kryterium sukcesu WCAG 2.1 – 1.2.4 Napisy rozszerzone (na żywo)",
      "assessmentType": "Kontrola",
      "preconditions": [
        ". ICT jest stroną internetową"
      ],
      "procedure": [
        ". Sprawdzić, czy strona internetowa spełnia kryterium sukcesu WCAG 2.1 – 1.2.4 Napisy rozszerzone (na żywo)"
      ],
      "results": [
        {
          "type": "Nie dotyczy",
          "label": "Nie spełniono warunku wstępnego 1 lub strona internetowa nie zawiera treści odpowiadającej kryterium sukcesu WCAG 2.1 – 1.2.4 Napisy rozszerzone (na żywo)"
        }
      ]
    },
    {
      "type": "test",
      "level": 5,
      "id": "res-c-9-1-2-5",
      "title": "Audiodeskrypcja (nagranie)",
      "text": ". Sprawdzić, czy strona internetowa spełnia kryterium sukcesu WCAG 2.1 – 1.2.5 Audiodeskrypcja (nagranie)",
      "assessmentType": "Kontrola",
      "preconditions": [
        ". ICT jest stroną internetową"
      ],
      "procedure": [
        ". Sprawdzić, czy strona internetowa spełnia kryterium sukcesu WCAG 2.1 – 1.2.5 Audiodeskrypcja (nagranie)"
      ],
      "results": [
        {
          "type": "Nie dotyczy",
          "label": "Nie spełniono warunku wstępnego 1 lub strona internetowa nie zawiera treści odpowiadającej kryterium sukcesu WCAG 2.1 – 1.2.5 Audiodeskrypcja (nagranie)"
        }
      ]
    },
    {
      "type": "heading",
      "level": 4,
      "id": "res-c-9-1-3",
      "title": "Możliwość adaptacji",
      "text": "Możliwość adaptacji"
    },
    {
      "type": "test",
      "level": 5,
      "id": "res-c-9-1-3-1",
      "title": "Informacje i relacje",
      "text": ". Sprawdzić, czy strona internetowa spełnia kryterium sukcesu WCAG 2.1 – 1.3.1 Informacje i relacje",
      "assessmentType": "Kontrola",
      "preconditions": [
        ". ICT jest stroną internetową"
      ],
      "procedure": [
        ". Sprawdzić, czy strona internetowa spełnia kryterium sukcesu WCAG 2.1 – 1.3.1 Informacje i relacje"
      ],
      "results": [
        {
          "type": "Nie dotyczy",
          "label": "Nie spełniono warunku wstępnego 1 lub strona internetowa nie zawiera treści odpowiadającej kryterium sukcesu WCAG 2.1 – 1.3.1 Informacje i relacje"
        }
      ]
    },
    {
      "type": "test",
      "level": 5,
      "id": "res-c-9-1-3-2",
      "title": "Zrozumiała kolejność",
      "text": ". Sprawdzić, czy strona internetowa spełnia kryterium sukcesu WCAG 2.1 – 1.3.2 Zrozumiała kolejność",
      "assessmentType": "Kontrola",
      "preconditions": [
        ". ICT jest stroną internetową"
      ],
      "procedure": [
        ". Sprawdzić, czy strona internetowa spełnia kryterium sukcesu WCAG 2.1 – 1.3.2 Zrozumiała kolejność"
      ],
      "results": [
        {
          "type": "Nie dotyczy",
          "label": "Nie spełniono warunku wstępnego 1 lub strona internetowa nie zawiera treści odpowiadającej kryterium sukcesu WCAG 2.1 – 1.3.2 Zrozumiała kolejność"
        }
      ]
    },
    {
      "type": "test",
      "level": 5,
      "id": "res-c-9-1-3-3",
      "title": "Właściwości zmysłowe",
      "text": ". Sprawdzić, czy strona internetowa spełnia kryterium sukcesu WCAG 2.1 – 1.3.3 Właściwości zmysłowe",
      "assessmentType": "Kontrola",
      "preconditions": [
        ". ICT jest stroną internetową"
      ],
      "procedure": [
        ". Sprawdzić, czy strona internetowa spełnia kryterium sukcesu WCAG 2.1 – 1.3.3 Właściwości zmysłowe"
      ],
      "results": [
        {
          "type": "Nie dotyczy",
          "label": "Nie spełniono warunku wstępnego 1 lub strona internetowa nie zawiera treści odpowiadającej kryterium sukcesu WCAG 2.1 – 1.3.3 Właściwości zmysłowe"
        }
      ]
    },
    {
      "type": "test",
      "level": 5,
      "id": "res-c-9-1-3-4",
      "title": "Orientacja",
      "text": ". Sprawdzić, czy strona internetowa spełnia kryterium sukcesu WCAG 2.1 – 1.3.4 Orientacja",
      "assessmentType": "Kontrola",
      "preconditions": [
        ". ICT jest stroną internetową"
      ],
      "procedure": [
        ". Sprawdzić, czy strona internetowa spełnia kryterium sukcesu WCAG 2.1 – 1.3.4 Orientacja"
      ],
      "results": [
        {
          "type": "Nie dotyczy",
          "label": "Nie spełniono warunku wstępnego 1 lub strona internetowa nie zawiera treści odpowiadającej kryterium sukcesu WCAG 2.1 – 1.3.4 Orientacja"
        }
      ]
    },
    {
      "type": "test",
      "level": 5,
      "id": "res-c-9-1-3-5",
      "title": "Określenie pożądanej wartości",
      "text": ". Sprawdzić, czy strona internetowa spełnia kryterium sukcesu WCAG 2.1 – 1.3.5 Określenie pożądanej wartości",
      "assessmentType": "Kontrola",
      "preconditions": [
        ". ICT jest stroną internetową"
      ],
      "procedure": [
        ". Sprawdzić, czy strona internetowa spełnia kryterium sukcesu WCAG 2.1 – 1.3.5 Określenie pożądanej wartości"
      ],
      "results": [
        {
          "type": "Nie dotyczy",
          "label": "Nie spełniono warunku wstępnego 1 lub strona internetowa nie zawiera treści odpowiadającej kryterium sukcesu WCAG 2.1 – 1.3.5 Określenie pożądanej wartości"
        }
      ]
    },
    {
      "type": "heading",
      "level": 4,
      "id": "res-c-9-1-4",
      "title": "Rozróżnialność",
      "text": "Rozróżnialność"
    },
    {
      "type": "test",
      "level": 5,
      "id": "res-c-9-1-4-1",
      "title": "Użycie koloru",
      "text": ". Sprawdzić, czy strona internetowa spełnia kryterium sukcesu WCAG 2.1 – 1.4.1 Użycie koloru",
      "assessmentType": "Kontrola",
      "preconditions": [
        ". ICT jest stroną internetową"
      ],
      "procedure": [
        ". Sprawdzić, czy strona internetowa spełnia kryterium sukcesu WCAG 2.1 – 1.4.1 Użycie koloru"
      ],
      "results": [
        {
          "type": "Nie dotyczy",
          "label": "Nie spełniono warunku wstępnego 1 lub strona internetowa nie zawiera treści odpowiadającej kryterium sukcesu WCAG 2.1 – 1.4.1 Użycie koloru"
        }
      ]
    },
    {
      "type": "test",
      "level": 5,
      "id": "res-c-9-1-4-2",
      "title": "Kontrola odtwarzania dźwięku",
      "text": ". Sprawdzić, czy strona internetowa spełnia kryterium sukcesu WCAG 2.1 – 1.4.2  odtwarzania dźwięku",
      "assessmentType": "Kontrola",
      "preconditions": [
        ". ICT jest stroną internetową"
      ],
      "procedure": [
        ". Sprawdzić, czy strona internetowa spełnia kryterium sukcesu WCAG 2.1 – 1.4.2  odtwarzania dźwięku"
      ],
      "results": [
        {
          "type": "Nie dotyczy",
          "label": "Nie spełniono warunku wstępnego 1 lub strona internetowa nie zawiera treści odpowiadającej kryterium sukcesu WCAG 2.1 – 1.4.2  odtwarzania dźwięku"
        }
      ]
    },
    {
      "type": "test",
      "level": 5,
      "id": "res-c-9-1-4-3",
      "title": "Kontrast (minimum)",
      "text": ". Sprawdzić, czy strona internetowa spełnia kryterium sukcesu WCAG 2.1 – 1.4.3 Kontrast (minimum)",
      "assessmentType": "Kontrola",
      "preconditions": [
        ". ICT jest stroną internetową"
      ],
      "procedure": [
        ". Sprawdzić, czy strona internetowa spełnia kryterium sukcesu WCAG 2.1 – 1.4.3 Kontrast (minimum)"
      ],
      "results": [
        {
          "type": "Nie dotyczy",
          "label": "Nie spełniono warunku wstępnego 1 lub strona internetowa nie zawiera treści odpowiadającej kryterium sukcesu WCAG 2.1 – 1.4.3 Kontrast (minimum)"
        }
      ]
    },
    {
      "type": "test",
      "level": 5,
      "id": "res-c-9-1-4-4",
      "title": "Zmiana rozmiaru tekstu",
      "text": ". ICT jest stroną internetową",
      "assessmentType": "Kontrola",
      "preconditions": [
        ". ICT jest stroną internetową"
      ],
      "procedure": [
        ". ICT jest stroną internetową",
        ". Sprawdzić, czy strona internetowa spełnia kryterium sukcesu WCAG 2.1 – 1.4.4 Zmiana rozmiaru tekstu"
      ],
      "results": [
        {
          "type": "Nie dotyczy",
          "label": "Nie spełniono warunku wstępnego 1 lub strona internetowa nie zawiera treści odpowiadającej kryterium sukcesu WCAG 2.1 – 1.4.4 Zmiana rozmiaru tekstu"
        }
      ]
    },
    {
      "type": "test",
      "level": 5,
      "id": "res-c-9-1-4-5",
      "title": "Obrazy tekstu",
      "text": ". Sprawdzić, czy strona internetowa spełnia kryterium sukcesu WCAG 2.1 – 1.4.5 Obrazy tekstu",
      "assessmentType": "Kontrola",
      "preconditions": [
        ". ICT jest stroną internetową"
      ],
      "procedure": [
        ". Sprawdzić, czy strona internetowa spełnia kryterium sukcesu WCAG 2.1 – 1.4.5 Obrazy tekstu"
      ],
      "results": [
        {
          "type": "Nie dotyczy",
          "label": "Nie spełniono warunku wstępnego 1 lub strona internetowa nie zawiera treści odpowiadającej kryterium sukcesu WCAG 2.1 – 1.4.5 Obrazy tekstu"
        }
      ]
    },
    {
      "type": "heading",
      "level": 5,
      "id": "res-c-9-1-4-6",
      "title": "Unieważniono",
      "text": "Unieważniono"
    },
    {
      "type": "heading",
      "level": 5,
      "id": "res-c-9-1-4-7",
      "title": "Unieważniono",
      "text": "Unieważniono"
    },
    {
      "type": "heading",
      "level": 5,
      "id": "res-c-9-1-4-8",
      "title": "Unieważniono",
      "text": "Unieważniono"
    },
    {
      "type": "heading",
      "level": 5,
      "id": "res-c-9-1-4-9",
      "title": "Unieważniono",
      "text": "Unieważniono"
    },
    {
      "type": "test",
      "level": 5,
      "id": "res-c-9-1-4-10",
      "title": "Dopasowanie do ekranu",
      "text": ". Sprawdzić, czy strona internetowa spełnia kryterium sukcesu WCAG 2.1 – 1.4.10 Dopasowanie do ekranu",
      "assessmentType": "Kontrola",
      "preconditions": [
        ". ICT jest stroną internetową"
      ],
      "procedure": [
        ". Sprawdzić, czy strona internetowa spełnia kryterium sukcesu WCAG 2.1 – 1.4.10 Dopasowanie do ekranu"
      ],
      "results": [
        {
          "type": "Nie dotyczy",
          "label": "Nie spełniono warunku wstępnego 1 lub strona internetowa nie zawiera treści odpowiadającej kryterium sukcesu WCAG 2.1 – 1.4.10 Dopasowanie do ekranu"
        }
      ]
    },
    {
      "type": "test",
      "level": 5,
      "id": "res-c-9-1-4-11",
      "title": "Kontrast elementów nietekstowych",
      "text": ". Sprawdzić, czy strona internetowa spełnia kryterium sukcesu WCAG 2.1 – 1.4.11 Kontrast elementów nietekstowych",
      "assessmentType": "Kontrola",
      "preconditions": [
        ". ICT jest stroną internetową"
      ],
      "procedure": [
        ". Sprawdzić, czy strona internetowa spełnia kryterium sukcesu WCAG 2.1 – 1.4.11 Kontrast elementów nietekstowych"
      ],
      "results": [
        {
          "type": "Nie dotyczy",
          "label": "Nie spełniono warunku wstępnego 1 lub strona internetowa nie zawiera treści odpowiadającej kryterium sukcesu WCAG 2.1 – 1.4.11 Kontrast elementów nietekstowych"
        }
      ]
    },
    {
      "type": "test",
      "level": 5,
      "id": "res-c-9-1-4-12",
      "title": "Odstępy w tekście",
      "text": ". Sprawdzić, czy strona internetowa spełnia kryterium sukcesu WCAG 2.1 – 1.4.12 Odstępy w tekście",
      "assessmentType": "Kontrola",
      "preconditions": [
        ". ICT jest stroną internetową"
      ],
      "procedure": [
        ". Sprawdzić, czy strona internetowa spełnia kryterium sukcesu WCAG 2.1 – 1.4.12 Odstępy w tekście"
      ],
      "results": [
        {
          "type": "Nie dotyczy",
          "label": "Nie spełniono warunku wstępnego 1 lub strona internetowa nie zawiera treści odpowiadającej kryterium sukcesu WCAG 2.1 – 1.4.12 Odstępy w tekście"
        }
      ]
    },
    {
      "type": "test",
      "level": 5,
      "id": "res-c-9-1-4-13",
      "title": "Treść spod kursora lub fokusu",
      "text": ". Sprawdzić, czy strona internetowa spełnia kryterium sukcesu WCAG 2.1 – 1.4.13 Treść spod kursora lub fokusu",
      "assessmentType": "Kontrola",
      "preconditions": [
        ". ICT jest stroną internetową"
      ],
      "procedure": [
        ". Sprawdzić, czy strona internetowa spełnia kryterium sukcesu WCAG 2.1 – 1.4.13 Treść spod kursora lub fokusu"
      ],
      "results": [
        {
          "type": "Nie dotyczy",
          "label": "Nie spełniono warunku wstępnego 1 lub strona internetowa nie zawiera treści odpowiadającej kryterium sukcesu WCAG 2.1 – 1.4.13 Treść spod kursora"
        }
      ]
    },
    {
      "type": "heading",
      "level": 3,
      "id": "res-c-9-2",
      "title": "Funkcjonalność",
      "text": "Funkcjonalność"
    },
    {
      "type": "heading",
      "level": 4,
      "id": "res-c-9-2-1",
      "title": "Dostępność z klawiatury",
      "text": "Dostępność z klawiatury"
    },
    {
      "type": "test",
      "level": 5,
      "id": "res-c-9-2-1-1",
      "title": "Klawiatura",
      "text": ". Sprawdzić, czy strona internetowa spełnia kryterium sukcesu WCAG 2.1 – 2.1.1 Klawiatura",
      "assessmentType": "Kontrola",
      "preconditions": [
        ". ICT jest stroną internetową"
      ],
      "procedure": [
        ". Sprawdzić, czy strona internetowa spełnia kryterium sukcesu WCAG 2.1 – 2.1.1 Klawiatura"
      ],
      "results": [
        {
          "type": "Nie dotyczy",
          "label": "Nie spełniono warunku wstępnego 1 lub strona internetowa nie zawiera treści odpowiadającej kryterium sukcesu WCAG 2.1 – 2.1.1 Klawiatura"
        }
      ]
    },
    {
      "type": "test",
      "level": 5,
      "id": "res-c-9-2-1-2",
      "title": "Bez pułapki na klawiaturę",
      "text": ". Sprawdzić, czy strona internetowa spełnia kryterium sukcesu WCAG 2.1 – 2.1.2 Bez pułapki na klawiaturę",
      "assessmentType": "Kontrola",
      "preconditions": [
        ". ICT jest stroną internetową"
      ],
      "procedure": [
        ". Sprawdzić, czy strona internetowa spełnia kryterium sukcesu WCAG 2.1 – 2.1.2 Bez pułapki na klawiaturę"
      ],
      "results": [
        {
          "type": "Nie dotyczy",
          "label": "Nie spełniono warunku wstępnego 1 lub strona internetowa nie zawiera treści odpowiadającej kryterium sukcesu WCAG 2.1 – 2.1.2 Bez pułapki na klawiaturę"
        }
      ]
    },
    {
      "type": "heading",
      "level": 5,
      "id": "res-c-9-2-1-3",
      "title": "Unieważniono",
      "text": "Unieważniono"
    },
    {
      "type": "test",
      "level": 5,
      "id": "res-c-9-2-1-4",
      "title": "Jednoznakowe skróty klawiaturowe",
      "text": ". Sprawdzić, czy strona internetowa spełnia kryterium sukcesu WCAG 2.1 – 2.1.4 Jednoznakowe skróty klawiaturowe",
      "assessmentType": "Kontrola",
      "preconditions": [
        ". ICT jest stroną internetową"
      ],
      "procedure": [
        ". Sprawdzić, czy strona internetowa spełnia kryterium sukcesu WCAG 2.1 – 2.1.4 Jednoznakowe skróty klawiaturowe"
      ],
      "results": [
        {
          "type": "Nie dotyczy",
          "label": "Nie spełniono warunku wstępnego 1 lub strona internetowa nie zawiera treści odpowiadającej kryterium sukcesu WCAG 2.1 – 2.1.4 Jednoznakowe skróty klawiaturowe"
        }
      ]
    },
    {
      "type": "heading",
      "level": 4,
      "id": "res-c-9-2-2",
      "title": "Wystarczający czas",
      "text": "Wystarczający czas"
    },
    {
      "type": "test",
      "level": 5,
      "id": "res-c-9-2-2-1",
      "title": "Dostosowanie czasu",
      "text": ". Sprawdzić, czy strona internetowa spełnia kryterium sukcesu WCAG 2.1 – 2.2.1 Dostosowanie czasu",
      "assessmentType": "Kontrola",
      "preconditions": [
        ". ICT jest stroną internetową"
      ],
      "procedure": [
        ". Sprawdzić, czy strona internetowa spełnia kryterium sukcesu WCAG 2.1 – 2.2.1 Dostosowanie czasu"
      ],
      "results": [
        {
          "type": "Nie dotyczy",
          "label": "Nie spełniono warunku wstępnego 1 lub strona internetowa nie zawiera treści odpowiadającej kryterium sukcesu WCAG 2.1 – 2.2.1 Dostosowanie czasu"
        }
      ]
    },
    {
      "type": "test",
      "level": 5,
      "id": "res-c-9-2-2-2",
      "title": "Pauza, zatrzymanie, ukrycie",
      "text": ". Sprawdzić, czy strona internetowa spełnia kryterium sukcesu WCAG 2.1 – 2.2.2 Pauza, zatrzymanie, ukrycie",
      "assessmentType": "Kontrola",
      "preconditions": [
        ". ICT jest stroną internetową"
      ],
      "procedure": [
        ". Sprawdzić, czy strona internetowa spełnia kryterium sukcesu WCAG 2.1 – 2.2.2 Pauza, zatrzymanie, ukrycie"
      ],
      "results": [
        {
          "type": "Nie dotyczy",
          "label": "Nie spełniono warunku wstępnego 1 lub strona internetowa nie zawiera treści odpowiadającej kryterium sukcesu WCAG 2.1 – 2.2.2 Pauza, zatrzymanie, ukrycie"
        }
      ]
    },
    {
      "type": "heading",
      "level": 4,
      "id": "res-c-9-2-3",
      "title": "Ataki padaczki",
      "text": "Ataki padaczki"
    },
    {
      "type": "test",
      "level": 5,
      "id": "res-c-9-2-3-1",
      "title": "Trzy błyski lub wartości poniżej progu",
      "text": ". Sprawdzić, czy strona internetowa spełnia kryterium sukcesu WCAG 2.1 – 2.3.1 Trzy błyski lub wartości poniżej progu",
      "assessmentType": "Kontrola",
      "preconditions": [
        ". ICT jest stroną internetową"
      ],
      "procedure": [
        ". Sprawdzić, czy strona internetowa spełnia kryterium sukcesu WCAG 2.1 – 2.3.1 Trzy błyski lub wartości poniżej progu"
      ],
      "results": [
        {
          "type": "Nie dotyczy",
          "label": "Nie spełniono warunku wstępnego 1 lub strona internetowa nie zawiera treści odpowiadającej kryterium sukcesu WCAG 2.1 – 2.3.1 Trzy błyski lub wartości poniżej progu"
        }
      ]
    },
    {
      "type": "heading",
      "level": 4,
      "id": "res-c-9-2-4",
      "title": "Możliwość nawigacji",
      "text": "Możliwość nawigacji"
    },
    {
      "type": "test",
      "level": 5,
      "id": "res-c-9-2-4-1",
      "title": "Możliwość pominięcia bloków",
      "text": ". Sprawdzić, czy strona internetowa spełnia kryterium sukcesu WCAG 2.1 – 2.4.1 Możliwość pominięcia boków",
      "assessmentType": "Kontrola",
      "preconditions": [
        ". ICT jest stroną internetową"
      ],
      "procedure": [
        ". Sprawdzić, czy strona internetowa spełnia kryterium sukcesu WCAG 2.1 – 2.4.1 Możliwość pominięcia boków"
      ],
      "results": [
        {
          "type": "Nie dotyczy",
          "label": "Nie spełniono warunku wstępnego 1 lub strona internetowa nie zawiera treści odpowiadającej kryterium sukcesu WCAG 2.1 – 2.4.1 Możliwość pominięcia bloków"
        }
      ]
    },
    {
      "type": "test",
      "level": 5,
      "id": "res-c-9-2-4-2",
      "title": "Tytuł strony",
      "text": ". Sprawdzić, czy strona internetowa spełnia kryterium sukcesu WCAG 2.1 – 2.4.2 Tytuł strony",
      "assessmentType": "Kontrola",
      "preconditions": [
        ". ICT jest stroną internetową"
      ],
      "procedure": [
        ". Sprawdzić, czy strona internetowa spełnia kryterium sukcesu WCAG 2.1 – 2.4.2 Tytuł strony"
      ],
      "results": [
        {
          "type": "Nie dotyczy",
          "label": "Nie spełniono warunku wstępnego 1 lub strona internetowa nie zawiera treści odpowiadającej kryterium sukcesu WCAG 2.1 – 2.4.2 Tytuł strony"
        }
      ]
    },
    {
      "type": "test",
      "level": 5,
      "id": "res-c-9-2-4-3",
      "title": "Kolejność fokusu",
      "text": ". Sprawdzić, czy strona internetowa spełnia kryterium sukcesu WCAG 2.1 – 2.4.3 Kolejność fokusu",
      "assessmentType": "Kontrola",
      "preconditions": [
        ". ICT jest stroną internetową"
      ],
      "procedure": [
        ". Sprawdzić, czy strona internetowa spełnia kryterium sukcesu WCAG 2.1 – 2.4.3 Kolejność fokusu"
      ],
      "results": [
        {
          "type": "Nie dotyczy",
          "label": "Nie spełniono warunku wstępnego 1 lub strona internetowa nie zawiera treści odpowiadającej kryterium sukcesu WCAG 2.1 – 2.4.3 Kolejność fokusu"
        }
      ]
    },
    {
      "type": "test",
      "level": 5,
      "id": "res-c-9-2-4-4",
      "title": "Cel łącza (w kontekście)",
      "text": ". Sprawdzić, czy strona internetowa spełnia kryterium sukcesu WCAG 2.1 – 2.4.4 Cel łącza (w kontekście)",
      "assessmentType": "Kontrola",
      "preconditions": [
        ". ICT jest stroną internetową"
      ],
      "procedure": [
        ". Sprawdzić, czy strona internetowa spełnia kryterium sukcesu WCAG 2.1 – 2.4.4 Cel łącza (w kontekście)"
      ],
      "results": [
        {
          "type": "Nie dotyczy",
          "label": "Nie spełniono warunku wstępnego 1 lub strona internetowa nie zawiera treści odpowiadającej kryterium sukcesu WCAG 2.1 – 2.4.4 Cel łącza (w kontekście)"
        }
      ]
    },
    {
      "type": "test",
      "level": 5,
      "id": "res-c-9-2-4-5",
      "title": "Wiele dróg",
      "text": ". Sprawdzić, czy strona internetowa spełnia kryterium sukcesu WCAG 2.1 – 2.4.5 Wiele dróg",
      "assessmentType": "Kontrola",
      "preconditions": [
        ". ICT jest stroną internetową"
      ],
      "procedure": [
        ". Sprawdzić, czy strona internetowa spełnia kryterium sukcesu WCAG 2.1 – 2.4.5 Wiele dróg"
      ],
      "results": [
        {
          "type": "Nie dotyczy",
          "label": "Nie spełniono warunku wstępnego 1 lub strona internetowa nie zawiera treści odpowiadającej kryterium sukcesu WCAG 2.1 – 2.4.5 Wiele dróg"
        }
      ]
    },
    {
      "type": "test",
      "level": 5,
      "id": "res-c-9-2-4-6",
      "title": "Nagłówki i etykiety",
      "text": ". Sprawdzić, czy strona internetowa spełnia kryterium sukcesu WCAG 2.1 – 2.4.6 Nagłówki i etykiety",
      "assessmentType": "Kontrola",
      "preconditions": [
        ". ICT jest stroną internetową"
      ],
      "procedure": [
        ". Sprawdzić, czy strona internetowa spełnia kryterium sukcesu WCAG 2.1 – 2.4.6 Nagłówki i etykiety"
      ],
      "results": [
        {
          "type": "Nie dotyczy",
          "label": "Nie spełniono warunku wstępnego 1 lub strona internetowa nie zawiera treści odpowiadającej kryterium sukcesu WCAG 2.1 – 2.4.6 Nagłówki i etykiety"
        }
      ]
    },
    {
      "type": "test",
      "level": 5,
      "id": "res-c-9-2-4-7",
      "title": "Widoczny fokus",
      "text": ". Sprawdzić, czy strona internetowa spełnia kryterium sukcesu WCAG 2.1 – 2.4.7 Widoczny fokus",
      "assessmentType": "Kontrola",
      "preconditions": [
        ". ICT jest stroną internetową"
      ],
      "procedure": [
        ". Sprawdzić, czy strona internetowa spełnia kryterium sukcesu WCAG 2.1 – 2.4.7 Widoczny fokus"
      ],
      "results": [
        {
          "type": "Nie dotyczy",
          "label": "Nie spełniono warunku wstępnego 1 lub strona internetowa nie zawiera treści odpowiadającej kryterium sukcesu WCAG 2.1 – 2.4.7 Widoczny fokus"
        }
      ]
    },
    {
      "type": "heading",
      "level": 4,
      "id": "res-c-9-2-5",
      "title": "Metody obsługi",
      "text": "Metody obsługi"
    },
    {
      "type": "test",
      "level": 5,
      "id": "res-c-9-2-5-1",
      "title": "Gesty dotykowe",
      "text": ". Sprawdzić, czy strona internetowa spełnia kryterium sukcesu WCAG 2.1 – 2.5.1 Gesty dotykowe",
      "assessmentType": "Kontrola",
      "preconditions": [
        ". ICT jest stroną internetową"
      ],
      "procedure": [
        ". Sprawdzić, czy strona internetowa spełnia kryterium sukcesu WCAG 2.1 – 2.5.1 Gesty dotykowe"
      ],
      "results": [
        {
          "type": "Nie dotyczy",
          "label": "Nie spełniono warunku wstępnego 1 lub strona internetowa nie zawiera treści odpowiadającej kryterium sukcesu WCAG 2.1 – 2.5.1 Gesty dotykowe"
        }
      ]
    },
    {
      "type": "test",
      "level": 5,
      "id": "res-c-9-2-5-2",
      "title": "Rezygnacja ze wskazania",
      "text": ". Sprawdzić, czy strona internetowa spełnia kryterium sukcesu WCAG 2.1 – 2.5.2 Rezygnacja ze wskazania",
      "assessmentType": "Kontrola",
      "preconditions": [
        ". ICT jest stroną internetową"
      ],
      "procedure": [
        ". Sprawdzić, czy strona internetowa spełnia kryterium sukcesu WCAG 2.1 – 2.5.2 Rezygnacja ze wskazania"
      ],
      "results": [
        {
          "type": "Nie dotyczy",
          "label": "Nie spełniono warunku wstępnego 1 lub strona internetowa nie zawiera treści odpowiadającej kryterium sukcesu WCAG 2.1 – 2.5.2 Rezygnacja ze wskazania"
        }
      ]
    },
    {
      "type": "test",
      "level": 5,
      "id": "res-c-9-2-5-3",
      "title": "Etykieta w nazwie",
      "text": ". Sprawdzić, czy strona internetowa spełnia kryterium sukcesu WCAG 2.1 – 2.5.3 Etykieta w nazwie",
      "assessmentType": "Kontrola",
      "preconditions": [
        ". ICT jest stroną internetową"
      ],
      "procedure": [
        ". Sprawdzić, czy strona internetowa spełnia kryterium sukcesu WCAG 2.1 – 2.5.3 Etykieta w nazwie"
      ],
      "results": [
        {
          "type": "Nie dotyczy",
          "label": "Nie spełniono warunku wstępnego 1 lub strona internetowa nie zawiera treści odpowiadającej kryterium sukcesu WCAG 2.1 – 2.5.3 Etykieta w nazwie"
        }
      ]
    },
    {
      "type": "test",
      "level": 5,
      "id": "res-c-9-2-5-4",
      "title": "Aktywowanie ruchem",
      "text": ". Sprawdzić, czy strona internetowa spełnia kryterium sukcesu WCAG 2.1 – 2.5.4 Aktywowanie ruchem",
      "assessmentType": "Kontrola",
      "preconditions": [
        ". ICT jest stroną internetową"
      ],
      "procedure": [
        ". Sprawdzić, czy strona internetowa spełnia kryterium sukcesu WCAG 2.1 – 2.5.4 Aktywowanie ruchem"
      ],
      "results": [
        {
          "type": "Nie dotyczy",
          "label": "Nie spełniono warunku wstępnego 1 lub strona internetowa nie zawiera treści odpowiadającej kryterium sukcesu WCAG 2.1 – 2.5.4 Aktywowanie ruchem"
        }
      ]
    },
    {
      "type": "heading",
      "level": 3,
      "id": "res-c-9-3",
      "title": "Zrozumiałość",
      "text": "Zrozumiałość"
    },
    {
      "type": "heading",
      "level": 4,
      "id": "res-c-9-3-1",
      "title": "Możliwość odczytania",
      "text": "Możliwość odczytania"
    },
    {
      "type": "test",
      "level": 5,
      "id": "res-c-9-3-1-1",
      "title": "Język strony",
      "text": ". Sprawdzić, czy strona internetowa spełnia kryterium sukcesu WCAG 2.1 – 3.1.1 Język strony",
      "assessmentType": "Kontrola",
      "preconditions": [
        ". ICT jest stroną internetową"
      ],
      "procedure": [
        ". Sprawdzić, czy strona internetowa spełnia kryterium sukcesu WCAG 2.1 – 3.1.1 Język strony"
      ],
      "results": [
        {
          "type": "Nie dotyczy",
          "label": "Nie spełniono warunku wstępnego 1 lub strona internetowa nie zawiera treści odpowiadającej kryterium sukcesu WCAG 2.1 – 3.1.1 Język strony"
        }
      ]
    },
    {
      "type": "test",
      "level": 5,
      "id": "res-c-9-3-1-2",
      "title": "Język części",
      "text": ". Sprawdzić, czy strona internetowa spełnia kryterium sukcesu WCAG 2.1 – 3.1.2 Język części",
      "assessmentType": "Kontrola",
      "preconditions": [
        ". ICT jest stroną internetową"
      ],
      "procedure": [
        ". Sprawdzić, czy strona internetowa spełnia kryterium sukcesu WCAG 2.1 – 3.1.2 Język części"
      ],
      "results": [
        {
          "type": "Nie dotyczy",
          "label": "Nie spełniono warunku wstępnego 1 lub strona internetowa nie zawiera treści odpowiadającej kryterium sukcesu WCAG 2.1 – 3.1.2 Język części"
        }
      ]
    },
    {
      "type": "heading",
      "level": 4,
      "id": "res-c-9-3-2",
      "title": "Przewidywalność",
      "text": "Przewidywalność"
    },
    {
      "type": "test",
      "level": 5,
      "id": "res-c-9-3-2-1",
      "title": "Po otrzymaniu fokusu",
      "text": ". Sprawdzić, czy strona internetowa spełnia kryterium sukcesu WCAG 2.1 – 3.2.1 Po otrzymaniu fokusu",
      "assessmentType": "Kontrola",
      "preconditions": [
        ". ICT jest stroną internetową"
      ],
      "procedure": [
        ". Sprawdzić, czy strona internetowa spełnia kryterium sukcesu WCAG 2.1 – 3.2.1 Po otrzymaniu fokusu"
      ],
      "results": [
        {
          "type": "Nie dotyczy",
          "label": "Nie spełniono warunku wstępnego 1 lub strona internetowa nie zawiera treści odpowiadającej kryterium sukcesu WCAG 2.1 – 3.2.1 Po otrzymaniu fokusu"
        }
      ]
    },
    {
      "type": "test",
      "level": 5,
      "id": "res-c-9-3-2-2",
      "title": "Podczas wprowadzania danych",
      "text": ". Sprawdzić, czy strona internetowa spełnia kryterium sukcesu WCAG 2.1 – 3.2.2 Podczas wprowadzania danych",
      "assessmentType": "Kontrola",
      "preconditions": [
        ". ICT jest stroną internetową"
      ],
      "procedure": [
        ". Sprawdzić, czy strona internetowa spełnia kryterium sukcesu WCAG 2.1 – 3.2.2 Podczas wprowadzania danych"
      ],
      "results": [
        {
          "type": "Nie dotyczy",
          "label": "Nie spełniono warunku wstępnego 1 lub strona internetowa nie zawiera treści odpowiadającej kryterium sukcesu WCAG 2.1 – 3.2.2 Podczas wprowadzania danych"
        }
      ]
    },
    {
      "type": "test",
      "level": 5,
      "id": "res-c-9-3-2-3",
      "title": "Spójna nawigacja",
      "text": ". Sprawdzić, czy strona internetowa spełnia kryterium sukcesu WCAG 2.1 – 3.2.3 Spójna nawigacja",
      "assessmentType": "Kontrola",
      "preconditions": [
        ". ICT jest stroną internetową"
      ],
      "procedure": [
        ". Sprawdzić, czy strona internetowa spełnia kryterium sukcesu WCAG 2.1 – 3.2.3 Spójna nawigacja"
      ],
      "results": [
        {
          "type": "Nie dotyczy",
          "label": "Nie spełniono warunku wstępnego 1 lub strona internetowa nie zawiera treści odpowiadającej kryterium sukcesu WCAG 2.1 – 3.2.3 Spójna nawigacja"
        }
      ]
    },
    {
      "type": "test",
      "level": 5,
      "id": "res-c-9-3-2-4",
      "title": "Spójna identyfikacja",
      "text": ". Sprawdzić, czy strona internetowa spełnia kryterium sukcesu WCAG 2.1 – 3.2.4 Spójna identyfikacja",
      "assessmentType": "Kontrola",
      "preconditions": [
        ". ICT jest stroną internetową"
      ],
      "procedure": [
        ". Sprawdzić, czy strona internetowa spełnia kryterium sukcesu WCAG 2.1 – 3.2.4 Spójna identyfikacja"
      ],
      "results": [
        {
          "type": "Nie dotyczy",
          "label": "Nie spełniono warunku wstępnego 1 lub strona internetowa nie zawiera treści odpowiadającej kryterium sukcesu WCAG 2.1 – 3.2.4 Spójna identyfikacja"
        }
      ]
    },
    {
      "type": "heading",
      "level": 4,
      "id": "res-c-9-3-3",
      "title": "Pomoc przy wprowadzaniu informacji",
      "text": "Pomoc przy wprowadzaniu informacji"
    },
    {
      "type": "test",
      "level": 5,
      "id": "res-c-9-3-3-1",
      "title": "Identyfikacja błędu",
      "text": ". Sprawdzić, czy strona internetowa spełnia kryterium sukcesu WCAG 2.1 – 3.3.1 Identyfikacja błędu",
      "assessmentType": "Kontrola",
      "preconditions": [
        ". ICT jest stroną internetową"
      ],
      "procedure": [
        ". Sprawdzić, czy strona internetowa spełnia kryterium sukcesu WCAG 2.1 – 3.3.1 Identyfikacja błędu"
      ],
      "results": [
        {
          "type": "Nie dotyczy",
          "label": "Nie spełniono warunku wstępnego 1 lub strona internetowa nie zawiera treści odpowiadającej kryterium sukcesu WCAG 2.1 – 3.3.1 Identyfikacja błędu"
        }
      ]
    },
    {
      "type": "test",
      "level": 5,
      "id": "res-c-9-3-3-2",
      "title": "Etykiety lub instrukcje",
      "text": ". Sprawdzić, czy strona internetowa spełnia kryterium sukcesu WCAG 2.1 – 3.3.2 Etykiety lub instrukcje",
      "assessmentType": "Kontrola",
      "preconditions": [
        ". ICT jest stroną internetową"
      ],
      "procedure": [
        ". Sprawdzić, czy strona internetowa spełnia kryterium sukcesu WCAG 2.1 – 3.3.2 Etykiety lub instrukcje"
      ],
      "results": [
        {
          "type": "Nie dotyczy",
          "label": "Nie spełniono warunku wstępnego 1 lub strona internetowa nie zawiera treści odpowiadającej kryterium sukcesu WCAG 2.1 – 3.3.2 Etykiety lub instrukcje"
        }
      ]
    },
    {
      "type": "test",
      "level": 5,
      "id": "res-c-9-3-3-3",
      "title": "Sugestie korekty błędów",
      "text": ". Sprawdzić, czy strona internetowa spełnia kryterium sukcesu WCAG 2.1 – 3.3.3 Sugestie korekty błędów",
      "assessmentType": "Kontrola",
      "preconditions": [
        ". ICT jest stroną internetową"
      ],
      "procedure": [
        ". Sprawdzić, czy strona internetowa spełnia kryterium sukcesu WCAG 2.1 – 3.3.3 Sugestie korekty błędów"
      ],
      "results": [
        {
          "type": "Nie dotyczy",
          "label": "Nie spełniono warunku wstępnego 1 lub strona internetowa nie zawiera treści odpowiadającej kryterium sukcesu WCAG 2.1 – 3.3.3 Sugestie korekty błędów"
        }
      ]
    },
    {
      "type": "test",
      "level": 5,
      "id": "res-c-9-3-3-4",
      "title": "Zapobieganie błędom (prawnym, finansowym, w danych)",
      "text": ". Sprawdzić, czy strona internetowa spełnia kryterium sukcesu WCAG 2.1 – 3.3.4 Zapobieganie błędom (prawnym, finansowym, w danych)",
      "assessmentType": "Kontrola",
      "preconditions": [
        ". ICT jest stroną internetową"
      ],
      "procedure": [
        ". Sprawdzić, czy strona internetowa spełnia kryterium sukcesu WCAG 2.1 – 3.3.4 Zapobieganie błędom (prawnym, finansowym, w danych)"
      ],
      "results": [
        {
          "type": "Nie dotyczy",
          "label": "Nie spełniono warunku wstępnego 1 lub strona internetowa nie zawiera treści istotnych dla WCAG 2.1 Kryterium sukcesu 3.3.4 Zapobieganie błędom (prawnym, finansowym, w danych)"
        }
      ]
    },
    {
      "type": "heading",
      "level": 3,
      "id": "res-c-9-4",
      "title": "Solidność",
      "text": "Solidność"
    },
    {
      "type": "heading",
      "level": 4,
      "id": "res-c-9-4-1",
      "title": "Kompatybilność",
      "text": "Kompatybilność"
    },
    {
      "type": "test",
      "level": 5,
      "id": "res-c-9-4-1-1",
      "title": "Poprawność kodu",
      "text": ". Sprawdzić, czy strona internetowa spełnia kryterium sukcesu WCAG 2.1 – 4.1.1 Poprawność kodu",
      "assessmentType": "Kontrola",
      "preconditions": [
        ". ICT jest stroną internetową"
      ],
      "procedure": [
        ". Sprawdzić, czy strona internetowa spełnia kryterium sukcesu WCAG 2.1 – 4.1.1 Poprawność kodu"
      ],
      "results": [
        {
          "type": "Nie dotyczy",
          "label": "Nie spełniono warunku wstępnego 1 lub strona internetowa nie zawiera treści odpowiadającej kryterium sukcesu WCAG 2.1 – 4.1.1 Poprawność kodu"
        }
      ]
    },
    {
      "type": "test",
      "level": 5,
      "id": "res-c-9-4-1-2",
      "title": "Nazwa, rola, wartość",
      "text": ". Sprawdzić, czy strona internetowa spełnia kryterium sukcesu WCAG 2.1 – 4.1.2 Nazwa, rola, wartość",
      "assessmentType": "Kontrola",
      "preconditions": [
        ". ICT jest stroną internetową"
      ],
      "procedure": [
        ". Sprawdzić, czy strona internetowa spełnia kryterium sukcesu WCAG 2.1 – 4.1.2 Nazwa, rola, wartość"
      ],
      "results": [
        {
          "type": "Nie dotyczy",
          "label": "Nie spełniono warunku wstępnego 1 lub strona internetowa nie zawiera treści odpowiadającej kryterium sukcesu WCAG 2.1 – 4.1.2 Nazwa, rola, wartość"
        }
      ]
    },
    {
      "type": "test",
      "level": 5,
      "id": "res-c-9-4-1-3",
      "title": "Komunikaty o stanie",
      "text": ". Sprawdzić, czy strona internetowa spełnia kryterium sukcesu WCAG 2.1 – 4.1.3 Komunikaty o stanie",
      "assessmentType": "Kontrola",
      "preconditions": [
        ". ICT jest stroną internetową"
      ],
      "procedure": [
        ". Sprawdzić, czy strona internetowa spełnia kryterium sukcesu WCAG 2.1 – 4.1.3 Komunikaty o stanie"
      ],
      "results": [
        {
          "type": "Nie dotyczy",
          "label": "Nie spełniono warunku wstępnego 1 lub strona internetowa nie zawiera treści odpowiadającej kryterium sukcesu WCAG 2.1 – 4.1.3 Komunikaty o stanie"
        }
      ]
    },
    {
      "type": "heading",
      "level": 3,
      "text": "Kryteria sukcesu WCAG 2.1 – AAA (informacyjne)"
    },
    {
      "type": "test",
      "level": 3,
      "id": "res-c-9-6",
      "title": "Wymagania zgodności WCAG 2.1",
      "text": ". Sprawdzić, czy strona internetowa spełnia wymaganie zgodności wg WCAG 2.1 [5] „1: Poziom zgodności” na poziomie AA",
      "assessmentType": "Kontrola",
      "preconditions": [
        ". ICT jest stroną internetową"
      ],
      "procedure": [
        ". Sprawdzić, czy strona internetowa spełnia wymaganie zgodności wg WCAG 2.1 [5] „1: Poziom zgodności” na poziomie AA",
        ". Sprawdzić, czy strona internetowa spełnia wymaganie zgodności wg WCAG 2.1 [5] „2: Całe strony”",
        ". Sprawdzić, czy strona internetowa spełnia wymaganie zgodności wg WCAG 2.1 [5] „3: Całe procesy”",
        ". Sprawdzić, czy strona internetowa spełnia wymaganie zgodności wg WCAG 2.1 [5] „4: Użycie technologii obsługujących dostępność”",
        ". Sprawdzić, czy strona internetowa spełnia wymaganie zgodności wg WCAG 2.1 [5] „5: Bez zakłóceń”"
      ],
      "results": [
        {
          "type": "Nie dotyczy",
          "label": "Nie spełniono warunku wstępnego"
        }
      ]
    }
  ]
}